dictupdate/__init__.py
dictupdate/dict_templating.py
dictupdate/updater.py
dictupdate-0.0.4.dist-info/LICENSE
dictupdate-0.0.4.dist-info/METADATA
dictupdate-0.0.4.dist-info/WHEEL
dictupdate-0.0.4.dist-info/top_level.txt
dictupdate-0.0.4.dist-info/RECORD
